cep/__init__.py
cep/forms.py
cep/models.py
cep/parser.py
cep/locale/pt_BR/LC_MESSAGES/django.po
tests/__init__.py
tests/settings.py
tests/tests.py
django_cepfield-0.4.0.dist-info/LICENSE
django_cepfield-0.4.0.dist-info/METADATA
django_cepfield-0.4.0.dist-info/WHEEL
django_cepfield-0.4.0.dist-info/top_level.txt
django_cepfield-0.4.0.dist-info/RECORD
